[{
  "id": "idd01", 
  "title": "На сколько хорошо вы знаете Java",
  "description": "Тест на уровень знания языка программирования Java версии 8 и выше. Вопросы в нём распределены от простого к сложному. Сложность определялась по субъективному мнению автора. Вы, конечно, можете пользоваться Гуглом или любимой книжкой, но постарайтесь быть честными с собой — попробуйте решить всё без подсказок. В конце концов, это не экзамен.",
  "startText": "Пройдите тест на проверку знаний языка Java",
  "questions": [
    {
      "title": "Начнём с простого: что такое Java?",
      "type": "singleChoise",
      "right": 2,
      "img": "https://upload.wikimedia.org/wikipedia/ru/thumb/3/39/Java_logo.svg/1200px-Java_logo.svg.png",
      "variants": [
        "Мотоцикл",
        "Остров",
        "Язык программирования",
        "Чай"
      ]
    },
    {
      "title": "Какая популярная игра написана на Java?",
      "type": "text",
      "right": "minecraft",
      "img": ""
    },
    {
      "title": "Что будет в результате выполнения операции 2 + 2 == 5 && 12 / 4 == 3 || 2 == 5 % 3",
      "type": "singleChoise",
      "right": 1,
      "img": "",
      "variants": [
        "true",	
        "false",
        "null",	
        "0"
      ]
    },
    {
      "title": "Как правильно объявлять массивы?",
      "type": "multiChoise",
      "right": [ 2, 5, 4],
      "img": "",
      "variants": [
        "int[] array = new int[];",
      	"int[] array = int[];",	
      	"int[] array = new int[]{1,2,3,4,5};",	
      	"int[] array = 1,2,3,4,5;",	
      	"int[] array = new int[5];",	
      	"int[] array = {1,2,3,4,5};"
      ]
    }
  ]
},
{
  "id": "idd02", 
  "title": "Основы программирования #1",
  "questions": [
    {
      "title": "Какая общая цель написания программы?",
      "type": "singleChoise",
      "right": 2,
      "img": "",
      "variants": [
        "Вычисление заранее известного выражения",
        "Ускорение работы операционной системы",
        "Получение результатов выражения"
      ]
    },
    {
      "title": "Закончите утверждение: программа - это ...",
      "type": "singleChoise",
      "right": 1,
      "img": "",
      "variants": [
        "Фрагмент кода, к которому можно обратиться из другого места",
        "Последовательность данных и инструкций, предназначеннных для вычислительного устройства",
        "Часть памяти компьютера"
      ]
    },
    {
      "title": "Закончите утверждение: индексация элементов массива в языке JavaScript начинается с ...",
      "type": "singleChoise",
      "right": 2,
      "img": "",
      "variants": [
        "Программист сам задает индексацию",
        "Единицы",
        "Нуля"
      ]
    },
    {
      "title": "Какое свойство в языке JavaScript показывает количетсво элементов массива?",
      "type": "singleChoise",
      "right": 1,
      "img": "",
      "variants": [
        "count",	
        "length",
        "size"
      ]
    },
    {
      "title": "С какого ключевого слова начинается объйвление в языке JavaScript?",
      "type": "singleChoise",
      "right": 1,
      "img": "",
      "variants": [
        "do",
      	"var",	
      	"for"
      ]
    },
    {
      "title": "Закончите утверждение: функция в контексте программы - это ...",
      "type": "singleChoise",
      "right": 2,
      "img": "",
      "variants": [
        "Самостоятиельный элемент кода программы, основной целью, которого является оптимизация времени выполнения программы",
        "Оператор программы",
        "Самостоятельный элемент кода программы, который позволяет решатть подзадачу"
      ]
    },
    {
      "title": "Каковы основные свойства алгоритма?",
      "type": "singleChoise",
      "right": 0,
      "img": "",
      "variants": [
        "Массовость, результативность, конечность",
        "Функциональность, вложенность, ясность",
        "Общность, многогранность, конечность"
      ]
    },
    {
      "title": "Что такое ветвление",
      "type": "singleChoise",
      "right": 1,
      "img": "",
      "variants": [
        "Управляющая конструкция, вызывающая сама себя с целью выполнения определенного набора команд",
        "Управляющая конструкция, позволяющая выполнить определенный набор команд, в случае истинности логического выражения",
        "Управляющая конструкция, предназначеннная для организации многократного исполнения набора инструкций"
      ]
    },
    {
      "title": "Выберите операции языка JavaScript, возвращающие логический результат",
      "type": "singleChoise",
      "right": 2,
      "img": "",
      "variants": [
        "&&, ||, ++, --",
        "<, =, ==, >=",
        ">, >=, !, ||"
      ]
    }
  ]
},
{
  "id": "idd03",
  "title": "Основы программирования #2",
  "questions": [
    {
      "title": "Как записывается операция вычисления отстатка от деления в целых числах в языке JavaScript?",
      "type": "singleChoise",
      "right": 1,
      "img": "",
      "variants": [
        "mod",
        "%",
        "&"
      ]
    },
    {
      "title": "Выберите правильную запись присвоения целочисленного значения переменной в языке JavaScript?",
      "type": "singleChoise",
      "right": 1,
      "img": "",
      "variants": [
        "var temp = 1.0;",
        "var temp = 1;",
        "var temp = \"1\";"
      ]
    },
    {
      "title": "Закончите утвеждение: языки программирования можно разделить на",
      "type": "singleChoise",
      "right": 2,
      "img": "",
      "variants": [
        "Языки программирования не имеют разделения",
        "С - подобные, Java - подобные",
        "Низкоуровневые и высокоуровневые"
      ]
    },
    {
      "title": "Выберите недопустимое использование команды promt в языке JavaScript",
      "type": "singleChoise",
      "right": 0,
      "img": "",
      "variants": [
        "promt(\"this\" 1);",
        "promt(\"thisText\", 1);",
        "promt(\"this\", \"1\");"
      ]
    },
    {
      "title": "Закончите утверждение: все данные, с точки зрения программы можно разделить на:",
      "type": "singleChoise",
      "right": 2,
      "img": "",
      "variants": [
        "Простые и составные",
        "Двоичные и шестнадцатиричные",
        "Взходные и выходные"
      ]
    },
    {
      "title": "Выберите цикл со счетчиком в языке JavaScript",
      "type": "singleChoise",
      "right": 2,
      "img": "",
      "variants": [
        "do-while",
        "while",
        "for"
      ]
    },
    {
      "title": "Выберите команду в языке JavaScript, при помощи которой пользователь может выводить данные на экран в диалоговом окне",
      "type": "singleChoise",
      "right": 1,
      "img": "",
      "variants": [
        "var",
        "alert",
        "return"
      ]
    },
    {
      "title": "Что такое переменная?",
      "type": "singleChoise",
      "right": 0,
      "img": "",
      "variants": [
        "Именнованая область памяти, адрес которой можно использовать ддля осуществления доступа к данным",
        "Инструкция, описывающая порядок действий для доступа к данным",
        "адрес, который хранит в себе ссылку на данные"
      ]
    },
    {
      "title": "В какой из \"библиотек\" в языке JavaScript находятся математические функции?",
      "type": "singleChoise",
      "right": 0,
      "img": "",
      "variants": [
        "Math",
        "Mathematic",
        "Matem"
      ]
    },
    {
      "title": "Какое значение будет присвоено переменной в результате выполнения операторов var res = 1 > 2 ? 1 : 2, в языке JavaScript",
      "type": "singleChoise",
      "right": 0,
      "img": "",
      "variants": [
        "2",
        "Ничего не будет присвоено. Запись ошибочна",
        "1"
      ]
    }
  ]
}]
